Workbook

Sheet Assumptions
A1: Lakebridge FP&A Forecast Assumptions
A3: Driver | B3: 2025E | C3: 2026E | D3: 2027E
A4: Unit volume | B4: 12000 | C4: 12900 | D4: 13700
A5: Average selling price ($) | B5: 48 | C5: 49 | D5: 50
A6: Gross margin | B6: 0.46 | C6: 0.465 | D6: 0.47
A7: Operating expense ($) | B7: 130000 | C7: 134000 | D7: 138000
A8: DSO | B8: 44 | C8: 44 | D8: 43
A9: Interest rate | B9: 0.065 | C9: 0.065 | D9: 0.065

Sheet Revenue_Build
A1: Revenue and Gross Profit Build
A3: Metric | B3: 2025E | C3: 2026E | D3: 2027E
A4: Unit volume | B4: ='Assumptions'!B4 | C4: ='Assumptions'!C4 | D4: ='Assumptions'!D4
A5: Average selling price | B5: ='Assumptions'!B5 | C5: ='Assumptions'!C5 | D5: ='Assumptions'!D5
A6: Revenue | B6: =B4*B5 | C6: =C4*C5 | D6: =685000
A7: Gross profit | B7: =B6*'Assumptions'!B6 | C7: =C6*'Assumptions'!C6 | D7: =D6*'Assumptions'!D6
A8: Operating contribution | B8: =B7-'Assumptions'!B7 | C8: =C7-'Assumptions'!C7 | D8: =D7-'Assumptions'!D7

Sheet Working_Capital
A1: Working Capital Schedule
A3: Metric | B3: 2025E | C3: 2026E | D3: 2027E
A4: Revenue | B4: ='Revenue_Build'!B6 | C4: ='Revenue_Build'!C6 | D4: ='Revenue_Build'!D6
A5: Accounts receivable | B5: =B4/365*'Assumptions'!B8 | C5: =C4/365*'Assumptions'!C8 | D5: =D4/365*'Assumptions'!D8
A6: Change in accounts receivable | B6: =B5-58000 | C6: =C5-B5 | D6: =D5-C5
A7: Cash impact | B7: =-B6 | C7: =-C6 | D7: =-D6

Sheet Debt_Schedule
A1: Debt and Interest Schedule
A3: Metric | B3: 2025E | C3: 2026E | D3: 2027E
A4: Opening debt | B4: 220000 | C4: =B7 | D4: =C7
A5: Interest expense | B5: =B4*'Assumptions'!B9 | C5: =C4*'Assumptions'!C9 | D5: =D4*'Assumptions'!D9
A6: Principal repayment | B6: 15000 | C6: 18000 | D6: 20000
A7: Closing debt | B7: =B4-B6 | C7: =C4-C6 | D7: =D4-D6

Sheet Summary
A1: FP&A Summary
A3: Metric | B3: 2025E | C3: 2026E | D3: 2027E
A4: Revenue | B4: ='Revenue_Build'!B6 | C4: ='Revenue_Build'!C6 | D4: ='Revenue_Build'!D6
A5: Operating contribution | B5: ='Revenue_Build'!B8 | C5: ='Revenue_Build'!C8 | D5: ='Revenue_Build'!D8
A6: Cash impact from working capital | B6: ='Working_Capital'!B7 | C6: ='Working_Capital'!C7 | D6: ='Working_Capital'!D7
A7: Interest expense | B7: ='Debt_Schedule'!B5 | C7: ='Debt_Schedule'!C5 | D7: ='Debt_Schedule'!D5
A8: Free cash flow before debt repayment | B8: =B5+B6-B7 | C8: =C5+C6-C7 | D8: =D5+D6-D7
A9: Debt service coverage | B9: =B8/'Debt_Schedule'!B6 | C9: =C8/'Debt_Schedule'!C6 | D9: =D8/'Debt_Schedule'!D6

Sheet Checks
A1: Repair and Integrity Checks
A3: Check | B3: Actual | C3: Expected | D3: Status | E3: Notes
A4: Integrated output tie-out | B4: ='Summary'!D4-('Assumptions'!D4*'Assumptions'!D5) | C4: 0 | D4: =IF(ABS(B4-C4)<0.01,"PASS","CHECK") | E4: Trace upstream forecast drivers
A5: Working-capital cash impact | B5: ='Working_Capital'!D7+'Working_Capital'!D6 | C5: 0 | D5: =IF(ABS(B5)<0.01,"PASS","CHECK") | E5: Negative change in AR
A6: Summary FCF bridge | B6: ='Summary'!D8-('Summary'!D5+'Summary'!D6-'Summary'!D7) | C6: 0 | D6: =IF(ABS(B6)<0.01,"PASS","CHECK") | E6: Operating contribution + WC cash - interest
A7: No source assumption edits | E7: Assumptions are protected
