Workbook

Sheet Source_Data
A1: Northstar Components — Historical Financial Source Extract
A3: Metric ($m unless noted) | B3: FY2022A | C3: FY2023A | D3: FY2024A | E3: Source tag | F3: Source URL | G3: Note
A4: Revenue | B4: 394328 | C4: 383285 | D4: 391035 | E4: us-gaap:RevenueFromContractWithCustomerExcludingAssessedTax | F4: https://data.sec.gov/api/xbrl/companyfacts/CIK0000320193.json | G4: Apple Inc. Company Facts; task uses values as historical input
A5: Operating income | B5: 119955 | C5: 114301 | D5: 123216 | E5: us-gaap:OperatingIncomeLoss | F5: https://data.sec.gov/api/xbrl/companyfacts/CIK0000320193.json | G5: Historical margin anchor
A6: D&A | B6: 11104 | C6: 11519 | D6: 11445 | E6: us-gaap:DepreciationDepletionAndAmortization | F6: https://data.sec.gov/api/xbrl/companyfacts/CIK0000320193.json | G6: Cash-flow input
A7: Capital expenditures | B7: 10708 | C7: 10959 | D7: 9447 | E7: us-gaap:PaymentsToAcquirePropertyPlantAndEquipment | F7: https://data.sec.gov/api/xbrl/companyfacts/CIK0000320193.json | G7: Cash-flow input
A8: Cash | B8: 23646 | C8: 29965 | D8: 29943 | E8: us-gaap:CashAndCashEquivalentsAtCarryingValue | F8: https://data.sec.gov/api/xbrl/companyfacts/CIK0000320193.json | G8: Equity bridge input

Sheet Assumptions
A1: DCF Assumptions
A3: Assumption | B3: 2025E | C3: 2026E | D3: 2027E | E3: 2028E | F3: 2029E | G3: Source / convention
A4: Revenue growth | B4: 0.06 | C4: 0.055 | D4: 0.05 | E4: 0.045 | F4: 0.04 | G4: Benchmark-authored forecast case
A5: EBIT margin | B5: 0.315 | C5: 0.317 | D5: 0.32 | E5: 0.322 | F5: 0.324 | G5: Held near FY2024 operating margin
A6: Tax rate | B6: 0.21 | C6: 0.21 | D6: 0.21 | E6: 0.21 | F6: 0.21 | G6: Normalized statutory rate
A7: D&A as % revenue | B7: 0.029 | C7: 0.029 | D7: 0.029 | E7: 0.029 | F7: 0.029 | G7: Historical anchor
A8: Capex as % revenue | B8: 0.027 | C8: 0.027 | D8: 0.027 | E8: 0.027 | F8: 0.027 | G8: Historical anchor
A9: Change in NWC as % revenue | B9: 0.012 | C9: 0.012 | D9: 0.012 | E9: 0.012 | F9: 0.012 | G9: Planning convention
A10: WACC | B10: 0.085 | G10: Applied to all forecast periods
A11: Terminal growth | B11: 0.025 | G11: Gordon growth convention

Sheet Forecast
A1: DCF Forecast and Unlevered Free Cash Flow
A4: Metric ($m unless noted) | B4: 2025E | C4: 2026E | D4: 2027E | E4: 2028E | F4: 2029E
A5: Revenue | B5: ='Source_Data'!D4*(1+'Assumptions'!B4) | C5: =B5*(1+'Assumptions'!C4) | D5: =C5*(1+'Assumptions'!D4) | E5: =D5*(1+'Assumptions'!E4) | F5: =499014.17783217004
A6: EBIT | B6: =B5*'Assumptions'!B5 | C6: =C5*'Assumptions'!C5 | D6: =D5*'Assumptions'!D5 | E6: =E5*'Assumptions'!E5 | F6: =F5*'Assumptions'!F5
A7: Cash taxes | B7: =B6*'Assumptions'!B6 | C7: =C6*'Assumptions'!C6 | D7: =D6*'Assumptions'!D6 | E7: =E6*'Assumptions'!E6 | F7: =F6*'Assumptions'!F6
A8: NOPAT | B8: =B6-B7 | C8: =C6-C7 | D8: =D6-D7 | E8: =E6-E7 | F8: =F6-F7
A9: D&A | B9: =B5*'Assumptions'!B7 | C9: =C5*'Assumptions'!C7 | D9: =D5*'Assumptions'!D7 | E9: =E5*'Assumptions'!E7 | F9: =F5*'Assumptions'!F7
A10: Capital expenditures | B10: =B5*'Assumptions'!B8 | C10: =C5*'Assumptions'!C8 | D10: =D5*'Assumptions'!D8 | E10: =E5*'Assumptions'!E8 | F10: =F5*'Assumptions'!F8
A11: Change in NWC | B11: =B5*'Assumptions'!B9 | C11: =C5*'Assumptions'!C9 | D11: =D5*'Assumptions'!D9 | E11: =E5*'Assumptions'!E9 | F11: =F5*'Assumptions'!F9
A12: Unlevered FCF | B12: =B8+B9-B10-B11 | C12: =C8+C9-C10-C11 | D12: =D8+D9-D10-D11 | E12: =E8+E9-E10-E11 | F12: =F8+F9-F10-F11
A13: Discount period | B13: 1 | C13: 2 | D13: 3 | E13: 4 | F13: 5
A14: Discount factor | B14: =1/(1+'Assumptions'!$B$10)^B13 | C14: =1/(1+'Assumptions'!$B$10)^C13 | D14: =1/(1+'Assumptions'!$B$10)^D13 | E14: =1/(1+'Assumptions'!$B$10)^E13 | F14: =1/(1+'Assumptions'!$B$10)^F13
A15: PV of UFCF | B15: =B12*B14 | C15: =C12*C14 | D15: =D12*D14 | E15: =E12*E14 | F15: =F12*F14

Sheet Valuation
A1: Enterprise and Equity Value
A4: Valuation bridge ($m) | B4: Value | C4: Sensitivity / supporting values
A5: PV of forecast UFCF | B5: =SUM('Forecast'!B15:F15) | C5: Terminal growth | D5: 0.02 | E5: 0.025 | F5: 0.03 | G5: WACC
A6: Terminal FCF | B6: ='Forecast'!F12*(1+'Assumptions'!$B$11) | C6: 0.075 | D6: =SUM('Forecast'!$B$12/(1+$C6)^'Forecast'!$B$13,'Forecast'!$C$12/(1+$C6)^'Forecast'!$C$13,'Forecast'!$D$12/(1+$C6)^'Forecast'!$D$13,'Forecast'!$E$12/(1+$C6)^'Forecast'!$E$13,'Forecast'!$F$12/(1+$C6)^'Forecast'!$F$13)+('Forecast'!$F$12*(1+D$5)/($C6-D$5))/(1+$C6)^'Forecast'!$F$13-'Valuation'!$B$12 | E6: =SUM('Forecast'!$B$12/(1+$C6)^'Forecast'!$B$13,'Forecast'!$C$12/(1+$C6)^'Forecast'!$C$13,'Forecast'!$D$12/(1+$C6)^'Forecast'!$D$13,'Forecast'!$E$12/(1+$C6)^'Forecast'!$E$13,'Forecast'!$F$12/(1+$C6)^'Forecast'!$F$13)+('Forecast'!$F$12*(1+E$5)/($C6-E$5))/(1+$C6)^'Forecast'!$F$13-'Valuation'!$B$12 | F6: =SUM('Forecast'!$B$12/(1+$C6)^'Forecast'!$B$13,'Forecast'!$C$12/(1+$C6)^'Forecast'!$C$13,'Forecast'!$D$12/(1+$C6)^'Forecast'!$D$13,'Forecast'!$E$12/(1+$C6)^'Forecast'!$E$13,'Forecast'!$F$12/(1+$C6)^'Forecast'!$F$13)+('Forecast'!$F$12*(1+F$5)/($C6-F$5))/(1+$C6)^'Forecast'!$F$13-'Valuation'!$B$12
A7: Terminal value | B7: =B6/('Assumptions'!$B$10-'Assumptions'!$B$11) | C7: 0.085 | D7: =SUM('Forecast'!$B$12/(1+$C7)^'Forecast'!$B$13,'Forecast'!$C$12/(1+$C7)^'Forecast'!$C$13,'Forecast'!$D$12/(1+$C7)^'Forecast'!$D$13,'Forecast'!$E$12/(1+$C7)^'Forecast'!$E$13,'Forecast'!$F$12/(1+$C7)^'Forecast'!$F$13)+('Forecast'!$F$12*(1+D$5)/($C7-D$5))/(1+$C7)^'Forecast'!$F$13-'Valuation'!$B$12 | E7: =SUM('Forecast'!$B$12/(1+$C7)^'Forecast'!$B$13,'Forecast'!$C$12/(1+$C7)^'Forecast'!$C$13,'Forecast'!$D$12/(1+$C7)^'Forecast'!$D$13,'Forecast'!$E$12/(1+$C7)^'Forecast'!$E$13,'Forecast'!$F$12/(1+$C7)^'Forecast'!$F$13)+('Forecast'!$F$12*(1+E$5)/($C7-E$5))/(1+$C7)^'Forecast'!$F$13-'Valuation'!$B$12 | F7: =SUM('Forecast'!$B$12/(1+$C7)^'Forecast'!$B$13,'Forecast'!$C$12/(1+$C7)^'Forecast'!$C$13,'Forecast'!$D$12/(1+$C7)^'Forecast'!$D$13,'Forecast'!$E$12/(1+$C7)^'Forecast'!$E$13,'Forecast'!$F$12/(1+$C7)^'Forecast'!$F$13)+('Forecast'!$F$12*(1+F$5)/($C7-F$5))/(1+$C7)^'Forecast'!$F$13-'Valuation'!$B$12
A8: PV of terminal value | B8: =B7*'Forecast'!F14 | C8: 0.095 | D8: =SUM('Forecast'!$B$12/(1+$C8)^'Forecast'!$B$13,'Forecast'!$C$12/(1+$C8)^'Forecast'!$C$13,'Forecast'!$D$12/(1+$C8)^'Forecast'!$D$13,'Forecast'!$E$12/(1+$C8)^'Forecast'!$E$13,'Forecast'!$F$12/(1+$C8)^'Forecast'!$F$13)+('Forecast'!$F$12*(1+D$5)/($C8-D$5))/(1+$C8)^'Forecast'!$F$13-'Valuation'!$B$12 | E8: =SUM('Forecast'!$B$12/(1+$C8)^'Forecast'!$B$13,'Forecast'!$C$12/(1+$C8)^'Forecast'!$C$13,'Forecast'!$D$12/(1+$C8)^'Forecast'!$D$13,'Forecast'!$E$12/(1+$C8)^'Forecast'!$E$13,'Forecast'!$F$12/(1+$C8)^'Forecast'!$F$13)+('Forecast'!$F$12*(1+E$5)/($C8-E$5))/(1+$C8)^'Forecast'!$F$13-'Valuation'!$B$12 | F8: =SUM('Forecast'!$B$12/(1+$C8)^'Forecast'!$B$13,'Forecast'!$C$12/(1+$C8)^'Forecast'!$C$13,'Forecast'!$D$12/(1+$C8)^'Forecast'!$D$13,'Forecast'!$E$12/(1+$C8)^'Forecast'!$E$13,'Forecast'!$F$12/(1+$C8)^'Forecast'!$F$13)+('Forecast'!$F$12*(1+F$5)/($C8-F$5))/(1+$C8)^'Forecast'!$F$13-'Valuation'!$B$12
A9: Enterprise value | B9: =1828520.50728509
A10: Cash | B10: ='Source_Data'!D8
A11: Debt (assumption) | B11: 97800
A12: Net debt | B12: =B11-B10
A13: Equity value | B13: =B9-B12

Sheet Checks
A1: DCF Model Checks
A3: Check | B3: Actual | C3: Expected | D3: Status | E3: Notes
A4: FCF component check | B4: ='Forecast'!F12-('Forecast'!F8+'Forecast'!F9-'Forecast'!F10-'Forecast'!F11) | C4: 0 | D4: =IF(ABS(B4-C4)<0.1,"PASS","CHECK") | E4: UFCF must be formula-derived from NOPAT, D&A, capex and NWC
A5: Terminal spread | B5: ='Assumptions'!$B$10-'Assumptions'!$B$11 | C5: 0 | D5: =IF(B5>0,"PASS","CHECK") | E5: WACC must exceed terminal growth
A6: Enterprise value formula | B6: ='Valuation'!B9-('Valuation'!B5+'Valuation'!B8) | D6: =IF(ABS(B6)<0.1,"PASS","CHECK") | E6: Forecast PV plus terminal PV
A7: Equity bridge | B7: ='Valuation'!B13-('Valuation'!B9-'Valuation'!B12) | D7: =IF(ABS(B7)<0.1,"PASS","CHECK") | E7: EV less net debt
A8: Source protection | E8: Historical source values must not be edited
